Metadata-Version: 1.0
Name: py-envfile
Version: 1.0.0
Summary: Python wrapper for .env
Home-page: UNKNOWN
Author: UNKNOWN
Author-email: UNKNOWN
License: UNKNOWN
Platform: UNKNOWN
